docs/source/conf.py
fuse/__init__.py
fuse/version.py
fuse/data/__init__.py
fuse/data/key_types.py
fuse/data/key_types_for_testing.py
fuse/data/patterns.py
fuse/data/datasets/__init__.py
fuse/data/datasets/dataset_base.py
fuse/data/datasets/dataset_default.py
fuse/data/datasets/dataset_wrap_seq_to_dict.py
fuse/data/datasets/sample_caching_audit.py
fuse/data/datasets/caching/__init__.py
fuse/data/datasets/caching/object_caching_handlers.py
fuse/data/datasets/caching/samples_cacher.py
fuse/data/datasets/caching/tests/__init__.py
fuse/data/datasets/caching/tests/test_sample_caching.py
fuse/data/datasets/tests/__init__.py
fuse/data/datasets/tests/test_dataset_default.py
fuse/data/datasets/tests/test_dataset_default_audit_feature.py
fuse/data/datasets/tests/test_dataset_wrap_seq_to_dict.py
fuse/data/ops/__init__.py
fuse/data/ops/caching_tools.py
fuse/data/ops/hashable_class.py
fuse/data/ops/op_base.py
fuse/data/ops/ops_aug_common.py
fuse/data/ops/ops_aug_tabular.py
fuse/data/ops/ops_cast.py
fuse/data/ops/ops_common.py
fuse/data/ops/ops_common_for_testing.py
fuse/data/ops/ops_debug.py
fuse/data/ops/ops_read.py
fuse/data/ops/tests/__init__.py
fuse/data/ops/tests/test_op_base.py
fuse/data/ops/tests/test_ops_aug_common.py
fuse/data/ops/tests/test_ops_cast.py
fuse/data/ops/tests/test_ops_common.py
fuse/data/ops/tests/test_ops_read.py
fuse/data/pipelines/__init__.py
fuse/data/pipelines/pipeline_default.py
fuse/data/pipelines/tests/__init__.py
fuse/data/pipelines/tests/test_pipeline_default.py
fuse/data/tests/__init__.py
fuse/data/tests/test_version.py
fuse/data/tokenizers/__init__.py
fuse/data/tokenizers/modular_tokenizer/__init__.py
fuse/data/tokenizers/modular_tokenizer/inject_utils.py
fuse/data/tokenizers/modular_tokenizer/modular_tokenizer.py
fuse/data/tokenizers/modular_tokenizer/op.py
fuse/data/tokenizers/modular_tokenizer/special_tokens.py
fuse/data/tokenizers/modular_tokenizer/scripts/add_multi_tokenizer_special_tokens.py
fuse_med_ml-0.4.0.dist-info/LICENSE.txt
fuse_med_ml-0.4.0.dist-info/METADATA
fuse_med_ml-0.4.0.dist-info/WHEEL
fuse_med_ml-0.4.0.dist-info/top_level.txt
fuse_med_ml-0.4.0.dist-info/RECORD
