Metadata-Version: 2.1
Name: fuse-med-ml
Version: 0.4.0
Summary: A python framework accelerating ML based discovery in the medical field by encouraging code reuse. Batteries included :)
Home-page: https://github.com/BiomedSciAI/fuse-med-ml/
Author: IBM Research - Machine Learning for Healthcare and Life Sciences
Author-email: moshiko.raboh@ibm.com
License: Apache License 2.0
Classifier: Programming Language :: Python :: 3.9
Classifier: Programming Language :: Python :: 3.10
Classifier: Programming Language :: Python :: 3.11
Requires-Python: >=3.9
License-File: LICENSE.txt
Requires-Dist: numpy >=1.18.5
Requires-Dist: pandas >=1.2
Requires-Dist: tqdm >=4.52.0
Requires-Dist: scipy >=1.5.4
Requires-Dist: matplotlib >=3.3.3
Requires-Dist: scikit-learn >=1.4
Requires-Dist: termcolor >=1.1.0
Requires-Dist: pycocotools >=2.0.1
Requires-Dist: pytorch-lightning >=1.6
Requires-Dist: torch
Requires-Dist: torchvision
Requires-Dist: tensorboard
Requires-Dist: wget
Requires-Dist: ipython
Requires-Dist: h5py
Requires-Dist: hdf5plugin
Requires-Dist: deepdiff
Requires-Dist: statsmodels
Requires-Dist: xmlrunner
Requires-Dist: paramiko
Requires-Dist: tables
Requires-Dist: psutil
Requires-Dist: ipykernel
Requires-Dist: hydra-core
Requires-Dist: omegaconf
Requires-Dist: nibabel
Requires-Dist: vit-pytorch
Requires-Dist: lifelines
Requires-Dist: clearml
Requires-Dist: x-transformers
Requires-Dist: jsonargparse
Requires-Dist: click
Provides-Extra: all
Requires-Dist: scikit-image >=0.17.2 ; extra == 'all'
Requires-Dist: SimpleITK >=1.2.0 ; extra == 'all'
Requires-Dist: opencv-python >=4.2.0.32 ; extra == 'all'
Requires-Dist: pydicom ; extra == 'all'
Requires-Dist: medpy ; extra == 'all'
Requires-Dist: plotly ; extra == 'all'
Requires-Dist: testbook ; extra == 'all'
Requires-Dist: mypy ==0.950 ; extra == 'all'
Requires-Dist: flake8 ; extra == 'all'
Requires-Dist: black ==22.3.0 ; extra == 'all'
Requires-Dist: pre-commit ; extra == 'all'
Requires-Dist: nb-clean ; extra == 'all'
Provides-Extra: dev
Requires-Dist: testbook ; extra == 'dev'
Requires-Dist: mypy ==0.950 ; extra == 'dev'
Requires-Dist: flake8 ; extra == 'dev'
Requires-Dist: black ==22.3.0 ; extra == 'dev'
Requires-Dist: pre-commit ; extra == 'dev'
Requires-Dist: nb-clean ; extra == 'dev'
Provides-Extra: examples
Requires-Dist: pydicom ; extra == 'examples'
Requires-Dist: scikit-image ; extra == 'examples'
Requires-Dist: medpy ; extra == 'examples'
Requires-Dist: transformers ; extra == 'examples'
Requires-Dist: monai ; extra == 'examples'
Requires-Dist: lightly ==1.3.0 ; extra == 'examples'
Requires-Dist: volumentations-3D ; extra == 'examples'
Provides-Extra: fuseimg
Requires-Dist: scikit-image >=0.17.2 ; extra == 'fuseimg'
Requires-Dist: SimpleITK >=1.2.0 ; extra == 'fuseimg'
Requires-Dist: opencv-python >=4.2.0.32 ; extra == 'fuseimg'
Requires-Dist: pydicom ; extra == 'fuseimg'
Requires-Dist: medpy ; extra == 'fuseimg'
Requires-Dist: plotly ; extra == 'fuseimg'
